pyxelletter/__init__.py
pyxelletter/pyxelletter.py
pyxelletter-0.6.2.dist-info/DESCRIPTION.rst
pyxelletter-0.6.2.dist-info/METADATA
pyxelletter-0.6.2.dist-info/RECORD
pyxelletter-0.6.2.dist-info/WHEEL
pyxelletter-0.6.2.dist-info/metadata.json
pyxelletter-0.6.2.dist-info/top_level.txt
