Metadata-Version: 2.0
Name: pyxelletter
Version: 0.6.2
Summary: A Python library for http://www.pixelletter.de/
Home-page: https://github.com/seibert-media/pyxelletter
Author: Nabil Nasri
Author-email: nnasri@seibert-media.net
License: Apache License 2.0
Platform: UNKNOWN
Requires-Dist: requests (==2.7.0)
